litesuite/__init__.py
litesuite/parselite/__init__.py
litesuite/parselite/main.py
litesuite-0.1.66.dist-info/METADATA
litesuite-0.1.66.dist-info/WHEEL
litesuite-0.1.66.dist-info/RECORD
